myarithmeticpkg1135/__init__.py
myarithmeticpkg1135/arithmetic.py
myarithmeticpkg1135/test_arithmetic.py
myarithmeticpkg1135-0.1.0.dist-info/LICENSE.txt
myarithmeticpkg1135-0.1.0.dist-info/METADATA
myarithmeticpkg1135-0.1.0.dist-info/WHEEL
myarithmeticpkg1135-0.1.0.dist-info/top_level.txt
myarithmeticpkg1135-0.1.0.dist-info/RECORD
